ipcvideo.cp39-win_amd64.pyd
ipcvideo-0.11.dist-info/METADATA
ipcvideo-0.11.dist-info/WHEEL
ipcvideo-0.11.dist-info/top_level.txt
ipcvideo-0.11.dist-info/RECORD
