Metadata-Version: 2.1
Name: ipcvideo
Version: 0.11
Summary: An open-source ipc(Interprocess Communication) video library.
Home-page: https://ipcvideo.blogspot.com/
Author: theo
Author-email: theo8028@gmail.com
